setup.py
hypermark/__init__.py
hypermark/api.py
hypermark/bootstrap.py
hypermark/core.py
hypermark/filters.py
hypermark/session.py
hypermark.egg-info/PKG-INFO
hypermark.egg-info/SOURCES.txt
hypermark.egg-info/dependency_links.txt
hypermark.egg-info/requires.txt
hypermark.egg-info/top_level.txt