Metadata-Version: 1.1
Name: hypermark
Version: 0.0.1
Summary: Markdown for Humans.
Home-page: https://github.com/kennethreitz/hypermark
Author: Kenneth Reitz
Author-email: me@kennethreitz.org
License: ISC
Platform: UNKNOWN
Classifier: Environment :: Console
Classifier: Intended Audience :: Developers
Classifier: Natural Language :: English
Classifier: License :: OSI Approved :: ISC License (ISCL)
Classifier: Programming Language :: Python
Classifier: Programming Language :: Python :: 2
Classifier: Programming Language :: Python :: 2.6
Classifier: Programming Language :: Python :: 2.7
Classifier: Programming Language :: Python :: 3
Classifier: Programming Language :: Python :: 3.1
Classifier: Programming Language :: Python :: 3.2
Classifier: Programming Language :: Python :: 3.3
Classifier: Programming Language :: Python :: 3.4
Classifier: Topic :: Terminals :: Terminal Emulators/X Terminals
